
<annotation>
    <folder>images</folder>
    <filename>circles25_aug_rupd_high_contrast_low_brightness.png</filename>
    <size>
        <width>400</width>
        <height>300</height>
        <depth>3</depth>
    </size>
    <segmented>0</segmented>
    <object>
        <name>circle</name>
        <pose>Unspecified</pose>
        <truncated>0</truncated>
        <occluded>0</occluded>
        <difficult>0</difficult>
        <bndbox>
            <xmin>361</xmin>
            <ymin>93</ymin>
            <xmax>390</xmax>
            <ymax>119</ymax>
        </bndbox>
    </object>
    <object>
        <name>circle</name>
        <pose>Unspecified</pose>
        <truncated>0</truncated>
        <occluded>0</occluded>
        <difficult>0</difficult>
        <bndbox>
            <xmin>357</xmin>
            <ymin>4</ymin>
            <xmax>389</xmax>
            <ymax>35</ymax>
        </bndbox>
    </object>
    <object>
        <name>circle</name>
        <pose>Unspecified</pose>
        <truncated>0</truncated>
        <occluded>0</occluded>
        <difficult>0</difficult>
        <bndbox>
            <xmin>300</xmin>
            <ymin>68</ymin>
            <xmax>327</xmax>
            <ymax>95</ymax>
        </bndbox>
    </object>
    <object>
        <name>circle</name>
        <pose>Unspecified</pose>
        <truncated>0</truncated>
        <occluded>0</occluded>
        <difficult>0</difficult>
        <bndbox>
            <xmin>289</xmin>
            <ymin>79</ymin>
            <xmax>316</xmax>
            <ymax>104</ymax>
        </bndbox>
    </object>
    <object>
        <name>circle</name>
        <pose>Unspecified</pose>
        <truncated>0</truncated>
        <occluded>0</occluded>
        <difficult>0</difficult>
        <bndbox>
            <xmin>266</xmin>
            <ymin>68</ymin>
            <xmax>292</xmax>
            <ymax>95</ymax>
        </bndbox>
    </object>
    <object>
        <name>circle</name>
        <pose>Unspecified</pose>
        <truncated>0</truncated>
        <occluded>0</occluded>
        <difficult>0</difficult>
        <bndbox>
            <xmin>260</xmin>
            <ymin>95</ymin>
            <xmax>286</xmax>
            <ymax>120</ymax>
        </bndbox>
    </object>
    <object>
        <name>circle</name>
        <pose>Unspecified</pose>
        <truncated>0</truncated>
        <occluded>0</occluded>
        <difficult>0</difficult>
        <bndbox>
            <xmin>312</xmin>
            <ymin>113</ymin>
            <xmax>338</xmax>
            <ymax>137</ymax>
        </bndbox>
    </object>
    <object>
        <name>circle</name>
        <pose>Unspecified</pose>
        <truncated>0</truncated>
        <occluded>0</occluded>
        <difficult>0</difficult>
        <bndbox>
            <xmin>281</xmin>
            <ymin>119</ymin>
            <xmax>306</xmax>
            <ymax>143</ymax>
        </bndbox>
    </object>
    <object>
        <name>circle</name>
        <pose>Unspecified</pose>
        <truncated>0</truncated>
        <occluded>0</occluded>
        <difficult>0</difficult>
        <bndbox>
            <xmin>272</xmin>
            <ymin>144</ymin>
            <xmax>297</xmax>
            <ymax>167</ymax>
        </bndbox>
    </object>
    <object>
        <name>circle</name>
        <pose>Unspecified</pose>
        <truncated>0</truncated>
        <occluded>0</occluded>
        <difficult>0</difficult>
        <bndbox>
            <xmin>284</xmin>
            <ymin>144</ymin>
            <xmax>308</xmax>
            <ymax>165</ymax>
        </bndbox>
    </object>
    <object>
        <name>circle</name>
        <pose>Unspecified</pose>
        <truncated>0</truncated>
        <occluded>0</occluded>
        <difficult>0</difficult>
        <bndbox>
            <xmin>303</xmin>
            <ymin>155</ymin>
            <xmax>329</xmax>
            <ymax>177</ymax>
        </bndbox>
    </object>
    <object>
        <name>circle</name>
        <pose>Unspecified</pose>
        <truncated>0</truncated>
        <occluded>0</occluded>
        <difficult>0</difficult>
        <bndbox>
            <xmin>334</xmin>
            <ymin>158</ymin>
            <xmax>358</xmax>
            <ymax>180</ymax>
        </bndbox>
    </object>
    <object>
        <name>circle</name>
        <pose>Unspecified</pose>
        <truncated>0</truncated>
        <occluded>0</occluded>
        <difficult>0</difficult>
        <bndbox>
            <xmin>321</xmin>
            <ymin>178</ymin>
            <xmax>345</xmax>
            <ymax>198</ymax>
        </bndbox>
    </object>
    <object>
        <name>circle</name>
        <pose>Unspecified</pose>
        <truncated>0</truncated>
        <occluded>0</occluded>
        <difficult>0</difficult>
        <bndbox>
            <xmin>301</xmin>
            <ymin>191</ymin>
            <xmax>325</xmax>
            <ymax>212</ymax>
        </bndbox>
    </object>
    <object>
        <name>circle</name>
        <pose>Unspecified</pose>
        <truncated>0</truncated>
        <occluded>0</occluded>
        <difficult>0</difficult>
        <bndbox>
            <xmin>281</xmin>
            <ymin>177</ymin>
            <xmax>304</xmax>
            <ymax>197</ymax>
        </bndbox>
    </object>
    <object>
        <name>circle</name>
        <pose>Unspecified</pose>
        <truncated>0</truncated>
        <occluded>0</occluded>
        <difficult>0</difficult>
        <bndbox>
            <xmin>258</xmin>
            <ymin>178</ymin>
            <xmax>281</xmax>
            <ymax>199</ymax>
        </bndbox>
    </object>
    <object>
        <name>circle</name>
        <pose>Unspecified</pose>
        <truncated>0</truncated>
        <occluded>0</occluded>
        <difficult>0</difficult>
        <bndbox>
            <xmin>248</xmin>
            <ymin>143</ymin>
            <xmax>273</xmax>
            <ymax>164</ymax>
        </bndbox>
    </object>
    <object>
        <name>circle</name>
        <pose>Unspecified</pose>
        <truncated>0</truncated>
        <occluded>0</occluded>
        <difficult>0</difficult>
        <bndbox>
            <xmin>223</xmin>
            <ymin>162</ymin>
            <xmax>246</xmax>
            <ymax>183</ymax>
        </bndbox>
    </object>
    <object>
        <name>circle</name>
        <pose>Unspecified</pose>
        <truncated>0</truncated>
        <occluded>0</occluded>
        <difficult>0</difficult>
        <bndbox>
            <xmin>205</xmin>
            <ymin>155</ymin>
            <xmax>228</xmax>
            <ymax>177</ymax>
        </bndbox>
    </object>
    <object>
        <name>circle</name>
        <pose>Unspecified</pose>
        <truncated>0</truncated>
        <occluded>0</occluded>
        <difficult>0</difficult>
        <bndbox>
            <xmin>217</xmin>
            <ymin>142</ymin>
            <xmax>240</xmax>
            <ymax>163</ymax>
        </bndbox>
    </object>
    <object>
        <name>circle</name>
        <pose>Unspecified</pose>
        <truncated>0</truncated>
        <occluded>0</occluded>
        <difficult>0</difficult>
        <bndbox>
            <xmin>238</xmin>
            <ymin>125</ymin>
            <xmax>263</xmax>
            <ymax>147</ymax>
        </bndbox>
    </object>
    <object>
        <name>circle</name>
        <pose>Unspecified</pose>
        <truncated>0</truncated>
        <occluded>0</occluded>
        <difficult>0</difficult>
        <bndbox>
            <xmin>232</xmin>
            <ymin>111</ymin>
            <xmax>257</xmax>
            <ymax>135</ymax>
        </bndbox>
    </object>
    <object>
        <name>circle</name>
        <pose>Unspecified</pose>
        <truncated>0</truncated>
        <occluded>0</occluded>
        <difficult>0</difficult>
        <bndbox>
            <xmin>222</xmin>
            <ymin>126</ymin>
            <xmax>246</xmax>
            <ymax>149</ymax>
        </bndbox>
    </object>
    <object>
        <name>circle</name>
        <pose>Unspecified</pose>
        <truncated>0</truncated>
        <occluded>0</occluded>
        <difficult>0</difficult>
        <bndbox>
            <xmin>216</xmin>
            <ymin>67</ymin>
            <xmax>243</xmax>
            <ymax>93</ymax>
        </bndbox>
    </object>
    <object>
        <name>circle</name>
        <pose>Unspecified</pose>
        <truncated>0</truncated>
        <occluded>0</occluded>
        <difficult>0</difficult>
        <bndbox>
            <xmin>180</xmin>
            <ymin>43</ymin>
            <xmax>208</xmax>
            <ymax>70</ymax>
        </bndbox>
    </object>
    <object>
        <name>circle</name>
        <pose>Unspecified</pose>
        <truncated>0</truncated>
        <occluded>0</occluded>
        <difficult>0</difficult>
        <bndbox>
            <xmin>158</xmin>
            <ymin>54</ymin>
            <xmax>183</xmax>
            <ymax>80</ymax>
        </bndbox>
    </object>
    <object>
        <name>circle</name>
        <pose>Unspecified</pose>
        <truncated>0</truncated>
        <occluded>0</occluded>
        <difficult>0</difficult>
        <bndbox>
            <xmin>134</xmin>
            <ymin>54</ymin>
            <xmax>158</xmax>
            <ymax>80</ymax>
        </bndbox>
    </object>
    <object>
        <name>circle</name>
        <pose>Unspecified</pose>
        <truncated>0</truncated>
        <occluded>0</occluded>
        <difficult>0</difficult>
        <bndbox>
            <xmin>118</xmin>
            <ymin>54</ymin>
            <xmax>143</xmax>
            <ymax>81</ymax>
        </bndbox>
    </object>
    <object>
        <name>circle</name>
        <pose>Unspecified</pose>
        <truncated>0</truncated>
        <occluded>0</occluded>
        <difficult>0</difficult>
        <bndbox>
            <xmin>41</xmin>
            <ymin>100</ymin>
            <xmax>64</xmax>
            <ymax>123</ymax>
        </bndbox>
    </object>
    <object>
        <name>circle</name>
        <pose>Unspecified</pose>
        <truncated>0</truncated>
        <occluded>0</occluded>
        <difficult>0</difficult>
        <bndbox>
            <xmin>84</xmin>
            <ymin>104</ymin>
            <xmax>107</xmax>
            <ymax>127</ymax>
        </bndbox>
    </object>
    <object>
        <name>circle</name>
        <pose>Unspecified</pose>
        <truncated>0</truncated>
        <occluded>0</occluded>
        <difficult>0</difficult>
        <bndbox>
            <xmin>115</xmin>
            <ymin>106</ymin>
            <xmax>139</xmax>
            <ymax>129</ymax>
        </bndbox>
    </object>
    <object>
        <name>circle</name>
        <pose>Unspecified</pose>
        <truncated>0</truncated>
        <occluded>0</occluded>
        <difficult>0</difficult>
        <bndbox>
            <xmin>205</xmin>
            <ymin>101</ymin>
            <xmax>230</xmax>
            <ymax>125</ymax>
        </bndbox>
    </object>
    <object>
        <name>circle</name>
        <pose>Unspecified</pose>
        <truncated>0</truncated>
        <occluded>0</occluded>
        <difficult>0</difficult>
        <bndbox>
            <xmin>198</xmin>
            <ymin>124</ymin>
            <xmax>221</xmax>
            <ymax>147</ymax>
        </bndbox>
    </object>
    <object>
        <name>circle</name>
        <pose>Unspecified</pose>
        <truncated>0</truncated>
        <occluded>0</occluded>
        <difficult>0</difficult>
        <bndbox>
            <xmin>185</xmin>
            <ymin>143</ymin>
            <xmax>208</xmax>
            <ymax>164</ymax>
        </bndbox>
    </object>
    <object>
        <name>circle</name>
        <pose>Unspecified</pose>
        <truncated>0</truncated>
        <occluded>0</occluded>
        <difficult>0</difficult>
        <bndbox>
            <xmin>180</xmin>
            <ymin>120</ymin>
            <xmax>203</xmax>
            <ymax>143</ymax>
        </bndbox>
    </object>
    <object>
        <name>circle</name>
        <pose>Unspecified</pose>
        <truncated>0</truncated>
        <occluded>0</occluded>
        <difficult>0</difficult>
        <bndbox>
            <xmin>158</xmin>
            <ymin>88</ymin>
            <xmax>183</xmax>
            <ymax>112</ymax>
        </bndbox>
    </object>
    <object>
        <name>circle</name>
        <pose>Unspecified</pose>
        <truncated>0</truncated>
        <occluded>0</occluded>
        <difficult>0</difficult>
        <bndbox>
            <xmin>132</xmin>
            <ymin>89</ymin>
            <xmax>156</xmax>
            <ymax>113</ymax>
        </bndbox>
    </object>
    <object>
        <name>circle</name>
        <pose>Unspecified</pose>
        <truncated>0</truncated>
        <occluded>0</occluded>
        <difficult>0</difficult>
        <bndbox>
            <xmin>145</xmin>
            <ymin>101</ymin>
            <xmax>169</xmax>
            <ymax>126</ymax>
        </bndbox>
    </object>
    <object>
        <name>circle</name>
        <pose>Unspecified</pose>
        <truncated>0</truncated>
        <occluded>0</occluded>
        <difficult>0</difficult>
        <bndbox>
            <xmin>156</xmin>
            <ymin>112</ymin>
            <xmax>181</xmax>
            <ymax>134</ymax>
        </bndbox>
    </object>
    <object>
        <name>circle</name>
        <pose>Unspecified</pose>
        <truncated>0</truncated>
        <occluded>0</occluded>
        <difficult>0</difficult>
        <bndbox>
            <xmin>156</xmin>
            <ymin>125</ymin>
            <xmax>179</xmax>
            <ymax>147</ymax>
        </bndbox>
    </object>
    <object>
        <name>circle</name>
        <pose>Unspecified</pose>
        <truncated>0</truncated>
        <occluded>0</occluded>
        <difficult>0</difficult>
        <bndbox>
            <xmin>162</xmin>
            <ymin>135</ymin>
            <xmax>185</xmax>
            <ymax>156</ymax>
        </bndbox>
    </object>
    <object>
        <name>circle</name>
        <pose>Unspecified</pose>
        <truncated>0</truncated>
        <occluded>0</occluded>
        <difficult>0</difficult>
        <bndbox>
            <xmin>260</xmin>
            <ymin>204</ymin>
            <xmax>282</xmax>
            <ymax>224</ymax>
        </bndbox>
    </object>
    <object>
        <name>circle</name>
        <pose>Unspecified</pose>
        <truncated>0</truncated>
        <occluded>0</occluded>
        <difficult>0</difficult>
        <bndbox>
            <xmin>254</xmin>
            <ymin>222</ymin>
            <xmax>276</xmax>
            <ymax>241</ymax>
        </bndbox>
    </object>
    <object>
        <name>circle</name>
        <pose>Unspecified</pose>
        <truncated>0</truncated>
        <occluded>0</occluded>
        <difficult>0</difficult>
        <bndbox>
            <xmin>228</xmin>
            <ymin>231</ymin>
            <xmax>249</xmax>
            <ymax>248</ymax>
        </bndbox>
    </object>
    <object>
        <name>circle</name>
        <pose>Unspecified</pose>
        <truncated>0</truncated>
        <occluded>0</occluded>
        <difficult>0</difficult>
        <bndbox>
            <xmin>133</xmin>
            <ymin>128</ymin>
            <xmax>156</xmax>
            <ymax>150</ymax>
        </bndbox>
    </object>
    <object>
        <name>circle</name>
        <pose>Unspecified</pose>
        <truncated>0</truncated>
        <occluded>0</occluded>
        <difficult>0</difficult>
        <bndbox>
            <xmin>133</xmin>
            <ymin>140</ymin>
            <xmax>156</xmax>
            <ymax>162</ymax>
        </bndbox>
    </object>
    <object>
        <name>circle</name>
        <pose>Unspecified</pose>
        <truncated>0</truncated>
        <occluded>0</occluded>
        <difficult>0</difficult>
        <bndbox>
            <xmin>101</xmin>
            <ymin>150</ymin>
            <xmax>124</xmax>
            <ymax>170</ymax>
        </bndbox>
    </object>
    <object>
        <name>circle</name>
        <pose>Unspecified</pose>
        <truncated>0</truncated>
        <occluded>0</occluded>
        <difficult>0</difficult>
        <bndbox>
            <xmin>182</xmin>
            <ymin>265</ymin>
            <xmax>202</xmax>
            <ymax>280</ymax>
        </bndbox>
    </object>
    <object>
        <name>circle</name>
        <pose>Unspecified</pose>
        <truncated>0</truncated>
        <occluded>0</occluded>
        <difficult>0</difficult>
        <bndbox>
            <xmin>181</xmin>
            <ymin>245</ymin>
            <xmax>201</xmax>
            <ymax>261</ymax>
        </bndbox>
    </object>
    <object>
        <name>circle</name>
        <pose>Unspecified</pose>
        <truncated>0</truncated>
        <occluded>0</occluded>
        <difficult>0</difficult>
        <bndbox>
            <xmin>238</xmin>
            <ymin>211</ymin>
            <xmax>259</xmax>
            <ymax>229</ymax>
        </bndbox>
    </object>
    <object>
        <name>circle</name>
        <pose>Unspecified</pose>
        <truncated>0</truncated>
        <occluded>0</occluded>
        <difficult>0</difficult>
        <bndbox>
            <xmin>210</xmin>
            <ymin>201</ymin>
            <xmax>232</xmax>
            <ymax>220</ymax>
        </bndbox>
    </object>
    <object>
        <name>circle</name>
        <pose>Unspecified</pose>
        <truncated>0</truncated>
        <occluded>0</occluded>
        <difficult>0</difficult>
        <bndbox>
            <xmin>239</xmin>
            <ymin>191</ymin>
            <xmax>262</xmax>
            <ymax>211</ymax>
        </bndbox>
    </object>
    <object>
        <name>circle</name>
        <pose>Unspecified</pose>
        <truncated>0</truncated>
        <occluded>0</occluded>
        <difficult>0</difficult>
        <bndbox>
            <xmin>232</xmin>
            <ymin>198</ymin>
            <xmax>254</xmax>
            <ymax>217</ymax>
        </bndbox>
    </object>
    <object>
        <name>circle</name>
        <pose>Unspecified</pose>
        <truncated>0</truncated>
        <occluded>0</occluded>
        <difficult>0</difficult>
        <bndbox>
            <xmin>75</xmin>
            <ymin>174</ymin>
            <xmax>97</xmax>
            <ymax>193</ymax>
        </bndbox>
    </object>
    <object>
        <name>circle</name>
        <pose>Unspecified</pose>
        <truncated>0</truncated>
        <occluded>0</occluded>
        <difficult>0</difficult>
        <bndbox>
            <xmin>103</xmin>
            <ymin>183</ymin>
            <xmax>124</xmax>
            <ymax>202</ymax>
        </bndbox>
    </object>
    <object>
        <name>circle</name>
        <pose>Unspecified</pose>
        <truncated>0</truncated>
        <occluded>0</occluded>
        <difficult>0</difficult>
        <bndbox>
            <xmin>97</xmin>
            <ymin>205</ymin>
            <xmax>118</xmax>
            <ymax>223</ymax>
        </bndbox>
    </object>
    <object>
        <name>circle</name>
        <pose>Unspecified</pose>
        <truncated>0</truncated>
        <occluded>0</occluded>
        <difficult>0</difficult>
        <bndbox>
            <xmin>110</xmin>
            <ymin>241</ymin>
            <xmax>130</xmax>
            <ymax>257</ymax>
        </bndbox>
    </object>
    <object>
        <name>circle</name>
        <pose>Unspecified</pose>
        <truncated>0</truncated>
        <occluded>0</occluded>
        <difficult>0</difficult>
        <bndbox>
            <xmin>128</xmin>
            <ymin>222</ymin>
            <xmax>148</xmax>
            <ymax>241</ymax>
        </bndbox>
    </object>
    <object>
        <name>circle</name>
        <pose>Unspecified</pose>
        <truncated>0</truncated>
        <occluded>0</occluded>
        <difficult>0</difficult>
        <bndbox>
            <xmin>141</xmin>
            <ymin>229</ymin>
            <xmax>162</xmax>
            <ymax>247</ymax>
        </bndbox>
    </object>
    <object>
        <name>circle</name>
        <pose>Unspecified</pose>
        <truncated>0</truncated>
        <occluded>0</occluded>
        <difficult>0</difficult>
        <bndbox>
            <xmin>165</xmin>
            <ymin>222</ymin>
            <xmax>185</xmax>
            <ymax>239</ymax>
        </bndbox>
    </object>
    <object>
        <name>circle</name>
        <pose>Unspecified</pose>
        <truncated>0</truncated>
        <occluded>0</occluded>
        <difficult>0</difficult>
        <bndbox>
            <xmin>186</xmin>
            <ymin>226</ymin>
            <xmax>207</xmax>
            <ymax>242</ymax>
        </bndbox>
    </object>
    <object>
        <name>circle</name>
        <pose>Unspecified</pose>
        <truncated>0</truncated>
        <occluded>0</occluded>
        <difficult>0</difficult>
        <bndbox>
            <xmin>182</xmin>
            <ymin>211</ymin>
            <xmax>203</xmax>
            <ymax>230</ymax>
        </bndbox>
    </object>
    <object>
        <name>circle</name>
        <pose>Unspecified</pose>
        <truncated>0</truncated>
        <occluded>0</occluded>
        <difficult>0</difficult>
        <bndbox>
            <xmin>208</xmin>
            <ymin>214</ymin>
            <xmax>229</xmax>
            <ymax>233</ymax>
        </bndbox>
    </object>
    <object>
        <name>circle</name>
        <pose>Unspecified</pose>
        <truncated>0</truncated>
        <occluded>0</occluded>
        <difficult>0</difficult>
        <bndbox>
            <xmin>197</xmin>
            <ymin>198</ymin>
            <xmax>217</xmax>
            <ymax>218</ymax>
        </bndbox>
    </object>
    <object>
        <name>circle</name>
        <pose>Unspecified</pose>
        <truncated>0</truncated>
        <occluded>0</occluded>
        <difficult>0</difficult>
        <bndbox>
            <xmin>162</xmin>
            <ymin>198</ymin>
            <xmax>182</xmax>
            <ymax>217</ymax>
        </bndbox>
    </object>
    <object>
        <name>circle</name>
        <pose>Unspecified</pose>
        <truncated>0</truncated>
        <occluded>0</occluded>
        <difficult>0</difficult>
        <bndbox>
            <xmin>132</xmin>
            <ymin>193</ymin>
            <xmax>153</xmax>
            <ymax>212</ymax>
        </bndbox>
    </object>
    <object>
        <name>circle</name>
        <pose>Unspecified</pose>
        <truncated>0</truncated>
        <occluded>0</occluded>
        <difficult>0</difficult>
        <bndbox>
            <xmin>214</xmin>
            <ymin>182</ymin>
            <xmax>235</xmax>
            <ymax>201</ymax>
        </bndbox>
    </object>
    <object>
        <name>circle</name>
        <pose>Unspecified</pose>
        <truncated>0</truncated>
        <occluded>0</occluded>
        <difficult>0</difficult>
        <bndbox>
            <xmin>195</xmin>
            <ymin>184</ymin>
            <xmax>217</xmax>
            <ymax>203</ymax>
        </bndbox>
    </object>
    <object>
        <name>circle</name>
        <pose>Unspecified</pose>
        <truncated>0</truncated>
        <occluded>0</occluded>
        <difficult>0</difficult>
        <bndbox>
            <xmin>192</xmin>
            <ymin>171</ymin>
            <xmax>214</xmax>
            <ymax>192</ymax>
        </bndbox>
    </object>
    <object>
        <name>circle</name>
        <pose>Unspecified</pose>
        <truncated>0</truncated>
        <occluded>0</occluded>
        <difficult>0</difficult>
        <bndbox>
            <xmin>178</xmin>
            <ymin>186</ymin>
            <xmax>199</xmax>
            <ymax>206</ymax>
        </bndbox>
    </object>
    <object>
        <name>circle</name>
        <pose>Unspecified</pose>
        <truncated>0</truncated>
        <occluded>0</occluded>
        <difficult>0</difficult>
        <bndbox>
            <xmin>156</xmin>
            <ymin>183</ymin>
            <xmax>179</xmax>
            <ymax>202</ymax>
        </bndbox>
    </object>
    <object>
        <name>circle</name>
        <pose>Unspecified</pose>
        <truncated>0</truncated>
        <occluded>0</occluded>
        <difficult>0</difficult>
        <bndbox>
            <xmin>168</xmin>
            <ymin>170</ymin>
            <xmax>191</xmax>
            <ymax>187</ymax>
        </bndbox>
    </object>
    <object>
        <name>circle</name>
        <pose>Unspecified</pose>
        <truncated>0</truncated>
        <occluded>0</occluded>
        <difficult>0</difficult>
        <bndbox>
            <xmin>170</xmin>
            <ymin>157</ymin>
            <xmax>192</xmax>
            <ymax>178</ymax>
        </bndbox>
    </object>
    <object>
        <name>circle</name>
        <pose>Unspecified</pose>
        <truncated>0</truncated>
        <occluded>0</occluded>
        <difficult>0</difficult>
        <bndbox>
            <xmin>153</xmin>
            <ymin>158</ymin>
            <xmax>175</xmax>
            <ymax>178</ymax>
        </bndbox>
    </object>
    <object>
        <name>circle</name>
        <pose>Unspecified</pose>
        <truncated>0</truncated>
        <occluded>0</occluded>
        <difficult>0</difficult>
        <bndbox>
            <xmin>140</xmin>
            <ymin>161</ymin>
            <xmax>162</xmax>
            <ymax>182</ymax>
        </bndbox>
    </object>
    <object>
        <name>circle</name>
        <pose>Unspecified</pose>
        <truncated>0</truncated>
        <occluded>0</occluded>
        <difficult>0</difficult>
        <bndbox>
            <xmin>138</xmin>
            <ymin>171</ymin>
            <xmax>159</xmax>
            <ymax>190</ymax>
        </bndbox>
    </object>
    <object>
        <name>circle</name>
        <pose>Unspecified</pose>
        <truncated>0</truncated>
        <occluded>0</occluded>
        <difficult>0</difficult>
        <bndbox>
            <xmin>127</xmin>
            <ymin>151</ymin>
            <xmax>147</xmax>
            <ymax>172</ymax>
        </bndbox>
    </object>
    <object>
        <name>circle</name>
        <pose>Unspecified</pose>
        <truncated>0</truncated>
        <occluded>0</occluded>
        <difficult>0</difficult>
        <bndbox>
            <xmin>119</xmin>
            <ymin>176</ymin>
            <xmax>140</xmax>
            <ymax>195</ymax>
        </bndbox>
    </object>
    <object>
        <name>circle</name>
        <pose>Unspecified</pose>
        <truncated>0</truncated>
        <occluded>0</occluded>
        <difficult>0</difficult>
        <bndbox>
            <xmin>116</xmin>
            <ymin>169</ymin>
            <xmax>137</xmax>
            <ymax>188</ymax>
        </bndbox>
    </object>
</annotation>